ulogcorn/.DS_Store
ulogcorn/__init__.py
ulogcorn/logger.py
ulogcorn-0.4.3.dist-info/LICENSE
ulogcorn-0.4.3.dist-info/WHEEL
ulogcorn-0.4.3.dist-info/METADATA
ulogcorn-0.4.3.dist-info/RECORD
