Metadata-Version: 2.1
Name: ulogcorn
Version: 0.4.3
Summary: Unify logging for a gunicorn and uvicorn application with loguru
Author: Joy
Author-email: icocoabeans@gmail.com
Requires-Python: >=3.7,<4.0
Classifier: Programming Language :: Python :: 3
Classifier: Programming Language :: Python :: 3.10
Classifier: Programming Language :: Python :: 3.7
Classifier: Programming Language :: Python :: 3.8
Classifier: Programming Language :: Python :: 3.9
Requires-Dist: gunicorn (>=20.1.0,<21.0.0)
Requires-Dist: loguru (>=0.6.0,<0.7.0)
Requires-Dist: uvicorn[standard] (>=0.18.1,<0.19.0)
